use_rabbitmq/__init__.py
use_rabbitmq-0.2.7.dist-info/METADATA
use_rabbitmq-0.2.7.dist-info/WHEEL
use_rabbitmq-0.2.7.dist-info/RECORD
